{
  "castle": {
    "size": [300, 320, 110],
    "building_initial_health": {
      "1": 200,
      "2": 400,
      "3": 600,
      "4": 800,
      "5": 1000
    },
    "resource_changes": {
      "gold": {
        "1": 10,
        "2": 15,
        "3": 20,
        "4": 25,
        "5": 30
      },
      "food": {
        "1": 2,
        "2": 4,
        "3": 6,
        "4": 8,
        "5": 10
      },
      "wood": {
        "1": 0,
        "2": 0,
        "3": 0,
        "4": 0,
        "5": 0
      }
    },
    "upgrade": {
      "gold": {
        "2": -50,
        "3": -150,
        "4": -300,
        "5": -500
      },
      "food": {
        "2": -50,
        "3": -120,
        "4": -200,
        "5": -300
      },
      "wood": {
        "2": -100,
        "3": -300,
        "4": -600,
        "5": -1000
      }
    }
  },
  "workshop": {
    "size": [91, 84, 30],
    "building_initial_health": {
      "1": 50,
      "2": 100,
      "3": 200,
      "4": 300,
      "5": 500
    },
    "resource_changes": {
      "gold": {
        "1": -5,
        "2": -10,
        "3": -15,
        "4": -20,
        "5": -25
      },
      "food": {
        "1": -5,
        "2": -5,
        "3": -5,
        "4": -5,
        "5": -5
      },
      "wood": {
        "1": 20,
        "2": 35,
        "3": 50,
        "4": 80,
        "5": 150
      }
    },
    "upgrade": {
      "gold": {
        "2": -5,
        "3": -15,
        "4": -30,
        "5": -50
      },
      "food": {
        "2": -10,
        "3": -30,
        "4": -60,
        "5": -100
      },
      "wood": {
        "2": -10,
        "3": -20,
        "4": -40,
        "5": -100
      }
    }
  },
  "barracks": {
    "size": [280, 180, 60],
    "building_initial_health": {
      "1": 100,
      "2": 200,
      "3": 300,
      "4": 400,
      "5": 500
    },
    "resource_changes": {
      "gold": {
        "1": 0,
        "2": 0,
        "3": 0,
        "4": 0,
        "5": 0
      },
      "food": {
        "1": 0,
        "2": 0,
        "3": 0,
        "4": 0,
        "5": 0
      },
      "wood": {
        "1": 0,
        "2": 0,
        "3": 0,
        "4": 0,
        "5": 0
      }
    },
    "upgrade": {
      "gold": {
        "2": -50,
        "3": -150,
        "4": -300,
        "5": -500
      },
      "food": {
        "2": -50,
        "3": -120,
        "4": -200,
        "5": -300
      },
      "wood": {
        "2": -100,
        "3": -300,
        "4": -600,
        "5": -1000
      }
    }
  },
  "farm": {
    "size": [233, 200, 60],
    "building_initial_health": {
      "1": 50,
      "2": 100,
      "3": 200,
      "4": 300,
      "5": 500
    },
    "resource_changes": {
      "gold": {
        "1": -5,
        "2": -10,
        "3": -15,
        "4": -20,
        "5": -25
      },
      "food": {
        "1": 30,
        "2": 50,
        "3": 100,
        "4": 180,
        "5": 300
      },
      "wood": {
        "1": 0,
        "2": 0,
        "3": 0,
        "4": 0,
        "5": 0
      }
    },
    "upgrade": {
      "gold": {
        "2": -5,
        "3": -15,
        "4": -30,
        "5": -50
      },
      "food": {
        "2": -10,
        "3": -30,
        "4": -60,
        "5": -100
      },
      "wood": {
        "2": -10,
        "3": -20,
        "4": -40,
        "5": -100
      }
    }
  }
}